opensolid/__init__.py
opensolid/opensolid-ffi.dll
opensolid/py.typed
opensolid-0.9.0.dist-info/METADATA
opensolid-0.9.0.dist-info/WHEEL
opensolid-0.9.0.dist-info/top_level.txt
opensolid-0.9.0.dist-info/RECORD
