Metadata-Version: 2.4
Name: opensolid
Version: 0.9.0
Summary: An under-development 2D/3D CAD library
Author-email: Ian Mackenzie <ian.e.mackenzie@gmail.com>
Project-URL: source, https://github.com/ianmackenzie/opensolid
Project-URL: documentation, https://opensolid.github.io/docs/0.9.0
Requires-Python: >=3.12
